MANIFEST.in
README.rst
setup.py
collective/__init__.py
collective.rtvideo.vimeo.egg-info/PKG-INFO
collective.rtvideo.vimeo.egg-info/SOURCES.txt
collective.rtvideo.vimeo.egg-info/dependency_links.txt
collective.rtvideo.vimeo.egg-info/entry_points.txt
collective.rtvideo.vimeo.egg-info/namespace_packages.txt
collective.rtvideo.vimeo.egg-info/not-zip-safe
collective.rtvideo.vimeo.egg-info/requires.txt
collective.rtvideo.vimeo.egg-info/top_level.txt
collective/rtvideo/__init__.py
collective/rtvideo/vimeo/__init__.py
collective/rtvideo/vimeo/configure.zcml
collective/rtvideo/vimeo/browser/__init__.py
collective/rtvideo/vimeo/browser/configure.zcml
collective/rtvideo/vimeo/browser/videoembedcode.py
collective/rtvideo/vimeo/browser/vimeoembedcode_template.pt
collective/rtvideo/vimeo/tests/__init__.py
collective/rtvideo/vimeo/tests/base.py
collective/rtvideo/vimeo/tests/test_videoembedcode.py
docs/HISTORY.rst
docs/INSTALL.txt
docs/LICENSE.GPL
docs/LICENSE.txt