Metadata-Version: 1.0
Name: collective.rtvideo.vimeo
Version: 0.2.0
Summary: The Vimeo Plone support for RedTurtle Video
Home-page: http://plone.org/products/redturtle.video
Author: RedTurtle Technology
Author-email: sviluppoplone@redturtle.it
License: GPL
Keywords: plone plonegov video embed vimeo
Platform: UNKNOWN
Classifier: Framework :: Plone
Classifier: Framework :: Plone :: 3.3
Classifier: Framework :: Plone :: 4.0
Classifier: Framework :: Plone :: 4.1
Classifier: Framework :: Plone :: 4.2
Classifier: Framework :: Plone :: 4.3
Classifier: Programming Language :: Python
Classifier: Topic :: Multimedia :: Video
Classifier: License :: OSI Approved :: GNU General Public License (GPL)
